flaskapp/__init__.py
flaskapp/config.py
flaskapp/create_project.py
flaskapp/base/__init__.py
flaskapp/base/app.py
flaskapp/base/requirements.txt
flaskapp/base/static/__init__.py
flaskapp/base/static/css/__init__.py
flaskapp/base/static/css/example.css
flaskapp/base/static/js/__init__.py
flaskapp/base/static/js/example.js
flaskapp/base/templates/__init__.py
flaskapp/base/templates/index.html
flaskapp-1.0.6.data/scripts/flaskapp
flaskapp-1.0.6.dist-info/METADATA
flaskapp-1.0.6.dist-info/WHEEL
flaskapp-1.0.6.dist-info/top_level.txt
flaskapp-1.0.6.dist-info/RECORD
